MANIFEST.in
README.md
setup.cfg
setup.py
commute_tube/__init__.py
commute_tube/__main__.py
commute_tube/commute_tube.py
commute_tube/file_utils.py
commute_tube.egg-info/PKG-INFO
commute_tube.egg-info/SOURCES.txt
commute_tube.egg-info/dependency_links.txt
commute_tube.egg-info/entry_points.txt
commute_tube.egg-info/requires.txt
commute_tube.egg-info/top_level.txt