Metadata-Version: 2.1
Name: commute-tube
Version: 1.6
Summary: UNKNOWN
Home-page: https://github.com/snipem/commute-tube
Author: Matthias Küch
Author-email: halde@matthias-kuech.de
License: GPL 3.0
Project-URL: Bug Reports, https://github.com/snipem/commute-tube/issues
Project-URL: Source, https://github.com/snipem/commute-tube/
Keywords: youtube-dl wrapper commute config datahoarding
Platform: UNKNOWN
Classifier: Development Status :: 5 - Production/Stable
Classifier: Intended Audience :: End Users/Desktop
Classifier: Programming Language :: Python :: 3
Classifier: License :: OSI Approved :: GNU General Public License v3 (GPLv3)
